odoo10_addon_delivery_dropoff_site-10.0.1.1.0-py3.6-nspkg.pth
odoo/addons/delivery_dropoff_site/README.rst
odoo/addons/delivery_dropoff_site/__init__.py
odoo/addons/delivery_dropoff_site/__manifest__.py
odoo/addons/delivery_dropoff_site/demo/delivery_carrier.xml
odoo/addons/delivery_dropoff_site/demo/dropoff_site.xml
odoo/addons/delivery_dropoff_site/demo/res_groups.xml
odoo/addons/delivery_dropoff_site/demo/resource_calendar.xml
odoo/addons/delivery_dropoff_site/i18n/delivery_dropoff_site.pot
odoo/addons/delivery_dropoff_site/i18n/fr.po
odoo/addons/delivery_dropoff_site/models/__init__.py
odoo/addons/delivery_dropoff_site/models/delivery_carrier.py
odoo/addons/delivery_dropoff_site/models/dropoff_site.py
odoo/addons/delivery_dropoff_site/models/procurement_group.py
odoo/addons/delivery_dropoff_site/models/res_partner.py
odoo/addons/delivery_dropoff_site/models/sale_order.py
odoo/addons/delivery_dropoff_site/models/stock_move.py
odoo/addons/delivery_dropoff_site/models/stock_picking.py
odoo/addons/delivery_dropoff_site/readme/CONFIGURE.rst
odoo/addons/delivery_dropoff_site/readme/CONTRIBUTORS.rst
odoo/addons/delivery_dropoff_site/readme/CREDITS.rst
odoo/addons/delivery_dropoff_site/readme/DESCRIPTION.rst
odoo/addons/delivery_dropoff_site/readme/USAGE.rst
odoo/addons/delivery_dropoff_site/security/ir.model.access.csv
odoo/addons/delivery_dropoff_site/static/description/dropoff_site_form.png
odoo/addons/delivery_dropoff_site/static/description/dropoff_site_form_calendar.png
odoo/addons/delivery_dropoff_site/static/description/dropoff_site_tree.png
odoo/addons/delivery_dropoff_site/static/description/icon.png
odoo/addons/delivery_dropoff_site/static/description/index.html
odoo/addons/delivery_dropoff_site/static/description/sale_order_form.png
odoo/addons/delivery_dropoff_site/views/view_delivery_carrier.xml
odoo/addons/delivery_dropoff_site/views/view_dropoff_site.xml
odoo/addons/delivery_dropoff_site/views/view_sale_order.xml
odoo10_addon_delivery_dropoff_site-10.0.1.1.0.dist-info/METADATA
odoo10_addon_delivery_dropoff_site-10.0.1.1.0.dist-info/WHEEL
odoo10_addon_delivery_dropoff_site-10.0.1.1.0.dist-info/namespace_packages.txt
odoo10_addon_delivery_dropoff_site-10.0.1.1.0.dist-info/top_level.txt
odoo10_addon_delivery_dropoff_site-10.0.1.1.0.dist-info/RECORD
